PyFJCore-1.0.1.dist-info/RECORD
PyFJCore-1.0.1.dist-info/LICENSE
PyFJCore-1.0.1.dist-info/WHEEL
PyFJCore-1.0.1.dist-info/top_level.txt
PyFJCore-1.0.1.dist-info/METADATA
pyfjcore/__init__.py
pyfjcore/pyfjcore.py
pyfjcore/_pyfjcore.cpython-37m-darwin.so
pyfjcore/.dylibs/libPyFJCore.dylib
